setup.cfg
setup.py
wordiscovery.py
wordiscovery.egg-info/PKG-INFO
wordiscovery.egg-info/SOURCES.txt
wordiscovery.egg-info/dependency_links.txt
wordiscovery.egg-info/top_level.txt