Metadata-Version: 1.1
Name: wordiscovery
Version: 0.1.4.6
Summary: A Chinese new word discovery
Home-page: https://github.com/ushiao/wordiscovery
Author: Kun JIN
Author-email: jin.kun@flykun.com
License: MIT
Keywords: NLP,new word discorvery
Platform: UNKNOWN
Classifier: Development Status :: 4 - Beta
Classifier: Intended Audience :: Developers
Classifier: Topic :: Software Development :: Build Tools
Classifier: License :: OSI Approved :: MIT License
Classifier: Programming Language :: Python :: 3
Classifier: Programming Language :: Python :: 3.3
Classifier: Programming Language :: Python :: 3.4
Classifier: Programming Language :: Python :: 3.5
